pyecma376_2/__init__.py
pyecma376_2/core_properties.py
pyecma376_2/package_model.py
pyecma376_2/py.typed
pyecma376_2/zip_package.py
pyecma376_2-1.0.0.dist-info/LICENSE
pyecma376_2-1.0.0.dist-info/METADATA
pyecma376_2-1.0.0.dist-info/WHEEL
pyecma376_2-1.0.0.dist-info/top_level.txt
pyecma376_2-1.0.0.dist-info/RECORD
