Metadata-Version: 2.1
Name: pyecma376-2
Version: 1.0.0
Summary: Library for reading and writing ECMA 376-2 (Open Packaging Conventions) files
Home-page: https://github.com/acplt/PyECMA376-2
Author: Chair of Information and Automation Systems for Process and Material Technology, RWTH Aachen University
Author-email: contact@plt.rwth-aachen.de
License: Apache License 2.0
Project-URL: Source, https://github.com/acplt/PyECMA376-2
Project-URL: Tracker, https://github.com/acplt/PyECMA376-2/issues
Classifier: Programming Language :: Python :: 3
Classifier: License :: OSI Approved :: Apache Software License
Classifier: Operating System :: OS Independent
Classifier: Development Status :: 5 - Production/Stable
Requires-Python: >=3.6
License-File: NOTICE
License-File: LICENSE
